mlm/__init__.py
mlm/_base_client.py
mlm/_client.py
mlm/_compat.py
mlm/_constants.py
mlm/_exceptions.py
mlm/_files.py
mlm/_models.py
mlm/_qs.py
mlm/_resource.py
mlm/_response.py
mlm/_streaming.py
mlm/_types.py
mlm/_version.py
mlm/py.typed
mlm/_utils/__init__.py
mlm/_utils/_logs.py
mlm/_utils/_proxy.py
mlm/_utils/_streams.py
mlm/_utils/_sync.py
mlm/_utils/_transform.py
mlm/_utils/_typing.py
mlm/_utils/_utils.py
mlm/lib/.keep
mlm/resources/__init__.py
mlm/resources/instances.py
mlm/resources/metrics.py
mlm/resources/models.py
mlm/types/__init__.py
mlm/types/instance_create_params.py
mlm/types/instance_create_response.py
mlm/types/instance_details.py
mlm/types/instance_list_response.py
mlm/types/instance_summary.py
mlm/types/instance_update_params.py
mlm/types/instance_update_response.py
mlm/types/metric_datapoint.py
mlm/types/metric_list_params.py
mlm/types/metric_list_response.py
mlm/types/model_create_params.py
mlm/types/model_create_response.py
mlm/types/model_details.py
mlm/types/model_list_response.py
mlm/types/model_summary.py
mlm/types/model_update_params.py
mlm/types/model_update_response.py
mlm_v1_0-0.1.0a0.dist-info/METADATA
mlm_v1_0-0.1.0a0.dist-info/WHEEL
mlm_v1_0-0.1.0a0.dist-info/licenses/LICENSE
mlm_v1_0-0.1.0a0.dist-info/RECORD
